src/__init__.py
src/main.py
tests/__init__.py
tests/test_add.py
pycidalp-1.0.2.dist-info/METADATA
pycidalp-1.0.2.dist-info/WHEEL
pycidalp-1.0.2.dist-info/top_level.txt
pycidalp-1.0.2.dist-info/RECORD
