Metadata-Version: 2.4
Name: pycidALP
Version: 1.0.2
Summary: Descripción de tu proyecto
Author: Angel Lorenzo-Penalva Lozano
Author-email: anglorloz@alu.edu.gva.es
Requires-Dist: pytest
Requires-Dist: flake8
Dynamic: author
Dynamic: author-email
Dynamic: requires-dist
Dynamic: summary
